cl1p/__init__.py
cl1p/cl1p.py
cl1p-0.7.dist-info/LICENSE
cl1p-0.7.dist-info/METADATA
cl1p-0.7.dist-info/WHEEL
cl1p-0.7.dist-info/entry_points.txt
cl1p-0.7.dist-info/top_level.txt
cl1p-0.7.dist-info/RECORD
