Metadata-Version: 2.1
Name: cl1p
Version: 0.7
Summary: Copy and paste using the internet
Home-page: https://github.com/maulik9898/cl1p
Author: Maulik Patel
Author-email: maulikp163@gmail.com
License: UNKNOWN
Platform: UNKNOWN
Classifier: Programming Language :: Python :: 3
Classifier: Programming Language :: Python :: 2
Classifier: License :: OSI Approved :: MIT License
Classifier: Operating System :: OS Independent
Requires-Dist: pyperclip
Requires-Dist: beautifulsoup4
Requires-Dist: colorama
Requires-Dist: requests
